kongodb/__init__.py
kongodb/adapters.py
kongodb/cursor.py
kongodb/database.py
kongodb/jsonquery.py
kongodb/lib.py
kongo-0.0.1.dist-info/LICENSE
kongo-0.0.1.dist-info/METADATA
kongo-0.0.1.dist-info/WHEEL
kongo-0.0.1.dist-info/top_level.txt
kongo-0.0.1.dist-info/RECORD
